gitstery/__init__.py
gitstery/__main__.py
gitstery/cli.py
gitstery/defines.py
gitstery/fillers.py
gitstery/git_utils.py
gitstery/people.py
gitstery/solution.py
gitstery/utils.py
gitstery/data/README.md
gitstery/data/book.txt
gitstery/data/given-names.txt
gitstery/data/instructions.txt
gitstery/data/interview-1.txt
gitstery/data/interview-2.txt
gitstery/data/interview-3.txt
gitstery/data/investigation-1.txt
gitstery/data/investigation-2.txt
gitstery/data/investigation-3.txt
gitstery/data/main-report.txt
gitstery/data/surnames.txt
gitstery/phases/__init__.py
gitstery/phases/phase_1.py
gitstery/phases/phase_2.py
gitstery/phases/phase_3.py
gitstery_generator-1.0.1.dist-info/LICENSE
gitstery_generator-1.0.1.dist-info/METADATA
gitstery_generator-1.0.1.dist-info/WHEEL
gitstery_generator-1.0.1.dist-info/entry_points.txt
gitstery_generator-1.0.1.dist-info/top_level.txt
gitstery_generator-1.0.1.dist-info/RECORD
