Metadata-Version: 2.1
Name: gitstery-generator
Version: 1.0.1
Summary: A Git murder mystery
Home-page: https://github.com/nivbend/gitstery-generator
Author: Niv Ben-David
Author-email: nivbend@gmail.com
License: GPLv3
Keywords: git mystery learn learning
Platform: UNKNOWN
Classifier: Development Status :: 1 - Planning
Classifier: Environment :: Console
Classifier: Intended Audience :: Developers
Classifier: Intended Audience :: Education
Classifier: License :: OSI Approved :: GNU General Public License v3 (GPLv3)
Classifier: Operating System :: POSIX :: Linux
Classifier: Operating System :: MacOS
Classifier: Operating System :: Microsoft :: Windows
Classifier: Programming Language :: Python
Classifier: Programming Language :: Python :: 3
Classifier: Topic :: Education
Classifier: Topic :: Games/Entertainment
Classifier: Topic :: Software Development
Classifier: Topic :: Software Development :: Version Control
Classifier: Topic :: Software Development :: Version Control :: Git
Classifier: Topic :: Terminals
Requires-Dist: Click (==7.0)
Requires-Dist: gitdb2 (==2.0.6)
Requires-Dist: GitPython (==3.0.5)
Requires-Dist: smmap2 (==2.0.5)
Requires-Dist: inflect (==4.1.0)
